simple_icinga_plugin/__init__.py
simple_icinga_plugin-0.4.1.dist-info/DESCRIPTION.rst
simple_icinga_plugin-0.4.1.dist-info/METADATA
simple_icinga_plugin-0.4.1.dist-info/RECORD
simple_icinga_plugin-0.4.1.dist-info/WHEEL
simple_icinga_plugin-0.4.1.dist-info/metadata.json
simple_icinga_plugin-0.4.1.dist-info/top_level.txt
