Metadata-Version: 2.0
Name: simple-icinga-plugin
Version: 0.4.1
Summary: simple icinga plugin helper module
Home-page: https://github.com/vshn/simple_icinga_plugin
Author: Andre Keller
Author-email: andre.keller@vshn.ch
License: BSD
Platform: UNKNOWN
Classifier: Development Status :: 3 - Alpha
Classifier: Intended Audience :: Developers
Classifier: Topic :: Software Development :: Build Tools
Classifier: License :: OSI Approved :: BSD License
Classifier: Programming Language :: Python :: 3
Classifier: Programming Language :: Python :: 3.2
Classifier: Programming Language :: Python :: 3.3
Classifier: Programming Language :: Python :: 3.4
